<?xml version='1.0' encoding='UTF-8'?>

<Robot Type='JulietteY20MP' RootNode='base_link'>


	<RobotNode name='AccelerometerBase_sensor_fixedjoint'>
		<Transform>
			<Matrix4x4 units='mm'>
				<row1 c1='1' c2='0' c3='0' c4='14.7' />
				<row2 c1='0' c2='1' c3='0' c4='-1.7' />
				<row3 c1='0' c2='0' c3='1' c4='-263.19' />
				<row4 c1='0' c2='0' c3='0' c4='1' />
			</Matrix4x4>
		</Transform>
		<Joint type='prismatic'>
			<translationdirection x='0' y='0' z='0'/>
			<limits lo='-3.14159' hi='3.14159' units='mm'/>
			<MaxAcceleration value='-1'/>
			<MaxVelocity value='-1'/>
			<MaxTorque value='-1'/>
		</Joint>
		<Child name='ImuBaseAccelerometer_frame'/>
	</RobotNode>


	<RobotNode name='Accelerometer_sensor_fixedjoint'>
		<Transform>
			<Matrix4x4 units='mm'>
				<row1 c1='1' c2='0' c3='0' c4='2.39' />
				<row2 c1='0' c2='1' c3='0' c4='-35.75' />
				<row3 c1='0' c2='0' c3='1' c4='145.26' />
				<row4 c1='0' c2='0' c3='0' c4='1' />
			</Matrix4x4>
		</Transform>
		<Joint type='prismatic'>
			<translationdirection x='0' y='0' z='0'/>
			<limits lo='-3.14159' hi='3.14159' units='mm'/>
			<MaxAcceleration value='-1'/>
			<MaxVelocity value='-1'/>
			<MaxTorque value='-1'/>
		</Joint>
		<Child name='ImuTorsoAccelerometer_frame'/>
	</RobotNode>


	<RobotNode name='Bumper/Back_sensor_fixedjoint'>
		<Transform>
			<Matrix4x4 units='mm'>
				<row1 c1='-1' c2='2.65359e-06' c3='0' c4='-251' />
				<row2 c1='-2.65359e-06' c2='-1' c3='-0' c4='0' />
				<row3 c1='-0' c2='0' c3='1' c4='-264' />
				<row4 c1='0' c2='0' c3='0' c4='1' />
			</Matrix4x4>
		</Transform>
		<Joint type='prismatic'>
			<translationdirection x='0' y='0' z='0'/>
			<limits lo='-3.14159' hi='3.14159' units='mm'/>
			<MaxAcceleration value='-1'/>
			<MaxVelocity value='-1'/>
			<MaxTorque value='-1'/>
		</Joint>
		<Child name='BumperB_frame'/>
	</RobotNode>


	<RobotNode name='Bumper/FrontLeft_sensor_fixedjoint'>
		<Transform>
			<Matrix4x4 units='mm'>
				<row1 c1='0.882869' c2='-0.46962' c3='0' c4='129' />
				<row2 c1='0.46962' c2='0.882869' c3='0' c4='227' />
				<row3 c1='0' c2='0' c3='1' c4='-264' />
				<row4 c1='0' c2='0' c3='0' c4='1' />
			</Matrix4x4>
		</Transform>
		<Joint type='prismatic'>
			<translationdirection x='0' y='0' z='0'/>
			<limits lo='-3.14159' hi='3.14159' units='mm'/>
			<MaxAcceleration value='-1'/>
			<MaxVelocity value='-1'/>
			<MaxTorque value='-1'/>
		</Joint>
		<Child name='BumperFL_frame'/>
	</RobotNode>


	<RobotNode name='Bumper/FrontRight_sensor_fixedjoint'>
		<Transform>
			<Matrix4x4 units='mm'>
				<row1 c1='0.882869' c2='0.46962' c3='0' c4='129' />
				<row2 c1='-0.46962' c2='0.882869' c3='-0' c4='-227' />
				<row3 c1='-0' c2='0' c3='1' c4='-264' />
				<row4 c1='0' c2='0' c3='0' c4='1' />
			</Matrix4x4>
		</Transform>
		<Joint type='prismatic'>
			<translationdirection x='0' y='0' z='0'/>
			<limits lo='-3.14159' hi='3.14159' units='mm'/>
			<MaxAcceleration value='-1'/>
			<MaxVelocity value='-1'/>
			<MaxTorque value='-1'/>
		</Joint>
		<Child name='BumperFR_frame'/>
	</RobotNode>


	<RobotNode name='BumperB_frame'>
		<Physics>
			<Mass unit='kg' value='0'/>
			<CoM location='Custom' x='0' y='0' z='0'/>
			<InertiaMatrix>
					<row1 c1='1' c2='0' c3='0'/>
					<row2 c1='0' c2='1' c3='0'/>
					<row3 c1='0' c2='0' c3='1'/>
			</InertiaMatrix>
		</Physics>
	</RobotNode>


	<RobotNode name='BumperFL_frame'>
		<Physics>
			<Mass unit='kg' value='0'/>
			<CoM location='Custom' x='0' y='0' z='0'/>
			<InertiaMatrix>
					<row1 c1='1' c2='0' c3='0'/>
					<row2 c1='0' c2='1' c3='0'/>
					<row3 c1='0' c2='0' c3='1'/>
			</InertiaMatrix>
		</Physics>
	</RobotNode>


	<RobotNode name='BumperFR_frame'>
		<Physics>
			<Mass unit='kg' value='0'/>
			<CoM location='Custom' x='0' y='0' z='0'/>
			<InertiaMatrix>
					<row1 c1='1' c2='0' c3='0'/>
					<row2 c1='0' c2='1' c3='0'/>
					<row3 c1='0' c2='0' c3='1'/>
			</InertiaMatrix>
		</Physics>
	</RobotNode>


	<RobotNode name='CameraBottom_frame'>
		<Physics>
			<Mass unit='kg' value='0'/>
			<CoM location='Custom' x='0' y='0' z='0'/>
			<InertiaMatrix>
					<row1 c1='1' c2='0' c3='0'/>
					<row2 c1='0' c2='1' c3='0'/>
					<row3 c1='0' c2='0' c3='1'/>
			</InertiaMatrix>
		</Physics>
		<Child name='CameraBottom_optical_frame_fixedjoint'/>
	</RobotNode>


	<RobotNode name='CameraBottom_optical_frame'>
		<Physics>
			<Mass unit='kg' value='0'/>
			<CoM location='Custom' x='0' y='0' z='0'/>
			<InertiaMatrix>
					<row1 c1='1' c2='0' c3='0'/>
					<row2 c1='0' c2='1' c3='0'/>
					<row3 c1='0' c2='0' c3='1'/>
			</InertiaMatrix>
		</Physics>
	</RobotNode>


	<RobotNode name='CameraBottom_optical_frame_fixedjoint'>
		<Transform>
			<Matrix4x4 units='mm'>
				<row1 c1='0' c2='0' c3='1' c4='0' />
				<row2 c1='-1' c2='0' c3='0' c4='0' />
				<row3 c1='0' c2='-1' c3='0' c4='0' />
				<row4 c1='0' c2='0' c3='0' c4='1' />
			</Matrix4x4>
		</Transform>
		<Joint type='prismatic'>
			<translationdirection x='0' y='0' z='0'/>
			<limits lo='-3.14159' hi='3.14159' units='mm'/>
			<MaxAcceleration value='-1'/>
			<MaxVelocity value='-1'/>
			<MaxTorque value='-1'/>
		</Joint>
		<Child name='CameraBottom_optical_frame'/>
	</RobotNode>


	<RobotNode name='CameraBottom_sensor_fixedjoint'>
		<Transform>
			<Matrix4x4 units='mm'>
				<row1 c1='0.766044' c2='0' c3='0.642788' c4='92.62' />
				<row2 c1='0' c2='1' c3='0' c4='0' />
				<row3 c1='-0.642788' c2='0' c3='0.766044' c4='61.77' />
				<row4 c1='0' c2='0' c3='0' c4='1' />
			</Matrix4x4>
		</Transform>
		<Joint type='prismatic'>
			<translationdirection x='0' y='0' z='0'/>
			<limits lo='-3.14159' hi='3.14159' units='mm'/>
			<MaxAcceleration value='-1'/>
			<MaxVelocity value='-1'/>
			<MaxTorque value='-1'/>
		</Joint>
		<Child name='CameraBottom_frame'/>
	</RobotNode>


	<RobotNode name='CameraDepth_frame'>
		<Physics>
			<Mass unit='kg' value='0'/>
			<CoM location='Custom' x='0' y='0' z='0'/>
			<InertiaMatrix>
					<row1 c1='1' c2='0' c3='0'/>
					<row2 c1='0' c2='1' c3='0'/>
					<row3 c1='0' c2='0' c3='1'/>
			</InertiaMatrix>
		</Physics>
		<Child name='CameraDepth_optical_frame_fixedjoint'/>
	</RobotNode>


	<RobotNode name='CameraDepth_optical_frame'>
		<Physics>
			<Mass unit='kg' value='0'/>
			<CoM location='Custom' x='0' y='0' z='0'/>
			<InertiaMatrix>
					<row1 c1='1' c2='0' c3='0'/>
					<row2 c1='0' c2='1' c3='0'/>
					<row3 c1='0' c2='0' c3='1'/>
			</InertiaMatrix>
		</Physics>
	</RobotNode>


	<RobotNode name='CameraDepth_optical_frame_fixedjoint'>
		<Transform>
			<Matrix4x4 units='mm'>
				<row1 c1='0' c2='0' c3='1' c4='0' />
				<row2 c1='-1' c2='0' c3='0' c4='0' />
				<row3 c1='0' c2='-1' c3='0' c4='0' />
				<row4 c1='0' c2='0' c3='0' c4='1' />
			</Matrix4x4>
		</Transform>
		<Joint type='prismatic'>
			<translationdirection x='0' y='0' z='0'/>
			<limits lo='-3.14159' hi='3.14159' units='mm'/>
			<MaxAcceleration value='-1'/>
			<MaxVelocity value='-1'/>
			<MaxTorque value='-1'/>
		</Joint>
		<Child name='CameraDepth_optical_frame'/>
	</RobotNode>


	<RobotNode name='CameraDepth_sensor_fixedjoint'>
		<Transform>
			<Matrix4x4 units='mm'>
				<row1 c1='1' c2='0' c3='0' c4='51.38' />
				<row2 c1='0' c2='1' c3='0' c4='39' />
				<row3 c1='0' c2='0' c3='1' c4='119.4' />
				<row4 c1='0' c2='0' c3='0' c4='1' />
			</Matrix4x4>
		</Transform>
		<Joint type='prismatic'>
			<translationdirection x='0' y='0' z='0'/>
			<limits lo='-3.14159' hi='3.14159' units='mm'/>
			<MaxAcceleration value='-1'/>
			<MaxVelocity value='-1'/>
			<MaxTorque value='-1'/>
		</Joint>
		<Child name='CameraDepth_frame'/>
	</RobotNode>


	<RobotNode name='CameraTop_frame'>
		<Physics>
			<Mass unit='kg' value='0'/>
			<CoM location='Custom' x='0' y='0' z='0'/>
			<InertiaMatrix>
					<row1 c1='1' c2='0' c3='0'/>
					<row2 c1='0' c2='1' c3='0'/>
					<row3 c1='0' c2='0' c3='1'/>
			</InertiaMatrix>
		</Physics>
		<Child name='CameraTop_optical_frame_fixedjoint'/>
	</RobotNode>


	<RobotNode name='CameraTop_optical_frame'>
		<Physics>
			<Mass unit='kg' value='0'/>
			<CoM location='Custom' x='0' y='0' z='0'/>
			<InertiaMatrix>
					<row1 c1='1' c2='0' c3='0'/>
					<row2 c1='0' c2='1' c3='0'/>
					<row3 c1='0' c2='0' c3='1'/>
			</InertiaMatrix>
		</Physics>
	</RobotNode>


	<RobotNode name='CameraTop_optical_frame_fixedjoint'>
		<Transform>
			<Matrix4x4 units='mm'>
				<row1 c1='0' c2='0' c3='1' c4='0' />
				<row2 c1='-1' c2='0' c3='0' c4='0' />
				<row3 c1='0' c2='-1' c3='0' c4='0' />
				<row4 c1='0' c2='0' c3='0' c4='1' />
			</Matrix4x4>
		</Transform>
		<Joint type='prismatic'>
			<translationdirection x='0' y='0' z='0'/>
			<limits lo='-3.14159' hi='3.14159' units='mm'/>
			<MaxAcceleration value='-1'/>
			<MaxVelocity value='-1'/>
			<MaxTorque value='-1'/>
		</Joint>
		<Child name='CameraTop_optical_frame'/>
	</RobotNode>


	<RobotNode name='CameraTop_sensor_fixedjoint'>
		<Transform>
			<Matrix4x4 units='mm'>
				<row1 c1='1' c2='0' c3='0' c4='86.01' />
				<row2 c1='0' c2='1' c3='0' c4='0' />
				<row3 c1='0' c2='0' c3='1' c4='162.84' />
				<row4 c1='0' c2='0' c3='0' c4='1' />
			</Matrix4x4>
		</Transform>
		<Joint type='prismatic'>
			<translationdirection x='0' y='0' z='0'/>
			<limits lo='-3.14159' hi='3.14159' units='mm'/>
			<MaxAcceleration value='-1'/>
			<MaxVelocity value='-1'/>
			<MaxTorque value='-1'/>
		</Joint>
		<Child name='CameraTop_frame'/>
	</RobotNode>


	<RobotNode name='ChestBoard/Button_sensor_fixedjoint'>
		<Transform>
			<Matrix4x4 units='mm'>
				<row1 c1='1' c2='0' c3='0' c4='49.871' />
				<row2 c1='0' c2='1' c3='0' c4='1.588' />
				<row3 c1='0' c2='0' c3='1' c4='194.163' />
				<row4 c1='0' c2='0' c3='0' c4='1' />
			</Matrix4x4>
		</Transform>
		<Joint type='prismatic'>
			<translationdirection x='0' y='0' z='0'/>
			<limits lo='-3.14159' hi='3.14159' units='mm'/>
			<MaxAcceleration value='-1'/>
			<MaxVelocity value='-1'/>
			<MaxTorque value='-1'/>
		</Joint>
		<Child name='ChestButton_frame'/>
	</RobotNode>


	<RobotNode name='ChestButton_frame'>
		<Physics>
			<Mass unit='kg' value='0'/>
			<CoM location='Custom' x='0' y='0' z='0'/>
			<InertiaMatrix>
					<row1 c1='1' c2='0' c3='0'/>
					<row2 c1='0' c2='1' c3='0'/>
					<row3 c1='0' c2='0' c3='1'/>
			</InertiaMatrix>
		</Physics>
	</RobotNode>


	<RobotNode name='Gyrometer_sensor_fixedjoint'>
		<Transform>
			<Matrix4x4 units='mm'>
				<row1 c1='1' c2='0' c3='0' c4='2.04' />
				<row2 c1='0' c2='1' c3='0' c4='-34.91' />
				<row3 c1='0' c2='0' c3='1' c4='129.41' />
				<row4 c1='0' c2='0' c3='0' c4='1' />
			</Matrix4x4>
		</Transform>
		<Joint type='prismatic'>
			<translationdirection x='0' y='0' z='0'/>
			<limits lo='-3.14159' hi='3.14159' units='mm'/>
			<MaxAcceleration value='-1'/>
			<MaxVelocity value='-1'/>
			<MaxTorque value='-1'/>
		</Joint>
		<Child name='ImuTorsoGyrometer_frame'/>
	</RobotNode>


	<RobotNode name='Head'>
		<Physics>
			<Mass unit='kg' value='1.51893'/>
			<CoM location='Custom' x='3.12' y='0' z='111.52'/>
			<InertiaMatrix>
					<row1 c1='0.00597209' c2='0' c3='0.000125138'/>
					<row2 c1='0' c2='0.0059054' c3='4.3428e-07'/>
					<row3 c1='0.000125138' c2='4.3428e-07' c3='0.00570374'/>
			</InertiaMatrix>
		</Physics>
		<Visualization>
			<File type='inventor'>models/Head_visu.wrl</File>
		</Visualization>
		<CollisionModel>
			<File type='inventor'>models/Head_col.wrl</File>
		</CollisionModel>
		<Child name='CameraBottom_sensor_fixedjoint'/>
		<Child name='CameraDepth_sensor_fixedjoint'/>
		<Child name='CameraTop_sensor_fixedjoint'/>
		<Child name='Head/Touch/Front_sensor_fixedjoint'/>
		<Child name='Head/Touch/Middle_sensor_fixedjoint'/>
		<Child name='Head/Touch/Rear_sensor_fixedjoint'/>
		<Child name='HeadPitch_ears_joint'/>
		<Child name='HeadPitch_milky_joint'/>
		<Child name='HeadPitch_shiny_joint'/>
		<Child name='SpeakerLeft_sensor_fixedjoint'/>
		<Child name='SpeakerRight_sensor_fixedjoint'/>
	</RobotNode>


	<RobotNode name='Head/Touch/Front_sensor_fixedjoint'>
		<Transform>
			<Matrix4x4 units='mm'>
				<row1 c1='0.978148' c2='0' c3='0.207912' c4='28.175' />
				<row2 c1='0' c2='1' c3='0' c4='0' />
				<row3 c1='-0.207912' c2='0' c3='0.978148' c4='212.67' />
				<row4 c1='0' c2='0' c3='0' c4='1' />
			</Matrix4x4>
		</Transform>
		<Joint type='prismatic'>
			<translationdirection x='0' y='0' z='0'/>
			<limits lo='-3.14159' hi='3.14159' units='mm'/>
			<MaxAcceleration value='-1'/>
			<MaxVelocity value='-1'/>
			<MaxTorque value='-1'/>
		</Joint>
		<Child name='HeadTouchFront_frame'/>
	</RobotNode>


	<RobotNode name='Head/Touch/Middle_sensor_fixedjoint'>
		<Transform>
			<Matrix4x4 units='mm'>
				<row1 c1='0.999391' c2='-0' c3='-0.0348995' c4='4.1' />
				<row2 c1='0' c2='1' c3='-0' c4='0' />
				<row3 c1='0.0348995' c2='0' c3='0.999391' c4='215.9' />
				<row4 c1='0' c2='0' c3='0' c4='1' />
			</Matrix4x4>
		</Transform>
		<Joint type='prismatic'>
			<translationdirection x='0' y='0' z='0'/>
			<limits lo='-3.14159' hi='3.14159' units='mm'/>
			<MaxAcceleration value='-1'/>
			<MaxVelocity value='-1'/>
			<MaxTorque value='-1'/>
		</Joint>
		<Child name='HeadTouchMiddle_frame'/>
	</RobotNode>


	<RobotNode name='Head/Touch/Rear_sensor_fixedjoint'>
		<Transform>
			<Matrix4x4 units='mm'>
				<row1 c1='0.951057' c2='-0' c3='-0.309017' c4='-33.76' />
				<row2 c1='0' c2='1' c3='-0' c4='0' />
				<row3 c1='0.309017' c2='0' c3='0.951057' c4='210.52' />
				<row4 c1='0' c2='0' c3='0' c4='1' />
			</Matrix4x4>
		</Transform>
		<Joint type='prismatic'>
			<translationdirection x='0' y='0' z='0'/>
			<limits lo='-3.14159' hi='3.14159' units='mm'/>
			<MaxAcceleration value='-1'/>
			<MaxVelocity value='-1'/>
			<MaxTorque value='-1'/>
		</Joint>
		<Child name='HeadTouchRear_frame'/>
	</RobotNode>


	<RobotNode name='HeadPitch'>
		<Joint type='revolute'>
			<axis x='0' y='1' z='0'/>
			<limits lo='-0.706858' hi='0.637045' units='radian'/>
			<MaxAcceleration value='-1'/>
			<MaxVelocity value='9.22756'/>
			<MaxTorque value='2.666'/>
		</Joint>
		<Child name='Head'/>
	</RobotNode>


	<RobotNode name='HeadPitch_ears'>
		<Physics>
			<Mass unit='kg' value='0'/>
			<CoM location='Custom' x='0' y='0' z='0'/>
			<InertiaMatrix>
					<row1 c1='1' c2='0' c3='0'/>
					<row2 c1='0' c2='1' c3='0'/>
					<row3 c1='0' c2='0' c3='1'/>
			</InertiaMatrix>
		</Physics>
	</RobotNode>


	<RobotNode name='HeadPitch_ears_joint'>
		<Joint type='prismatic'>
			<translationdirection x='0' y='0' z='0'/>
			<limits lo='-3.14159' hi='3.14159' units='mm'/>
			<MaxAcceleration value='-1'/>
			<MaxVelocity value='-1'/>
			<MaxTorque value='-1'/>
		</Joint>
		<Child name='HeadPitch_ears'/>
	</RobotNode>


	<RobotNode name='HeadPitch_milky'>
		<Physics>
			<Mass unit='kg' value='0'/>
			<CoM location='Custom' x='0' y='0' z='0'/>
			<InertiaMatrix>
					<row1 c1='1' c2='0' c3='0'/>
					<row2 c1='0' c2='1' c3='0'/>
					<row3 c1='0' c2='0' c3='1'/>
			</InertiaMatrix>
		</Physics>
	</RobotNode>


	<RobotNode name='HeadPitch_milky_joint'>
		<Joint type='prismatic'>
			<translationdirection x='0' y='0' z='0'/>
			<limits lo='-3.14159' hi='3.14159' units='mm'/>
			<MaxAcceleration value='-1'/>
			<MaxVelocity value='-1'/>
			<MaxTorque value='-1'/>
		</Joint>
		<Child name='HeadPitch_milky'/>
	</RobotNode>


	<RobotNode name='HeadPitch_shiny'>
		<Physics>
			<Mass unit='kg' value='0'/>
			<CoM location='Custom' x='0' y='0' z='0'/>
			<InertiaMatrix>
					<row1 c1='1' c2='0' c3='0'/>
					<row2 c1='0' c2='1' c3='0'/>
					<row3 c1='0' c2='0' c3='1'/>
			</InertiaMatrix>
		</Physics>
	</RobotNode>


	<RobotNode name='HeadPitch_shiny_joint'>
		<Joint type='prismatic'>
			<translationdirection x='0' y='0' z='0'/>
			<limits lo='-3.14159' hi='3.14159' units='mm'/>
			<MaxAcceleration value='-1'/>
			<MaxVelocity value='-1'/>
			<MaxTorque value='-1'/>
		</Joint>
		<Child name='HeadPitch_shiny'/>
	</RobotNode>


	<RobotNode name='HeadTouchFront_frame'>
		<Physics>
			<Mass unit='kg' value='0'/>
			<CoM location='Custom' x='0' y='0' z='0'/>
			<InertiaMatrix>
					<row1 c1='1' c2='0' c3='0'/>
					<row2 c1='0' c2='1' c3='0'/>
					<row3 c1='0' c2='0' c3='1'/>
			</InertiaMatrix>
		</Physics>
	</RobotNode>


	<RobotNode name='HeadTouchMiddle_frame'>
		<Physics>
			<Mass unit='kg' value='0'/>
			<CoM location='Custom' x='0' y='0' z='0'/>
			<InertiaMatrix>
					<row1 c1='1' c2='0' c3='0'/>
					<row2 c1='0' c2='1' c3='0'/>
					<row3 c1='0' c2='0' c3='1'/>
			</InertiaMatrix>
		</Physics>
	</RobotNode>


	<RobotNode name='HeadTouchRear_frame'>
		<Physics>
			<Mass unit='kg' value='0'/>
			<CoM location='Custom' x='0' y='0' z='0'/>
			<InertiaMatrix>
					<row1 c1='1' c2='0' c3='0'/>
					<row2 c1='0' c2='1' c3='0'/>
					<row3 c1='0' c2='0' c3='1'/>
			</InertiaMatrix>
		</Physics>
	</RobotNode>


	<RobotNode name='HeadYaw'>
		<Transform>
			<Matrix4x4 units='mm'>
				<row1 c1='1' c2='0' c3='0' c4='-38' />
				<row2 c1='0' c2='1' c3='0' c4='0' />
				<row3 c1='0' c2='0' c3='1' c4='308.9' />
				<row4 c1='0' c2='0' c3='0' c4='1' />
			</Matrix4x4>
		</Transform>
		<Joint type='revolute'>
			<axis x='0' y='0' z='1'/>
			<limits lo='-2.08567' hi='2.08567' units='radian'/>
			<MaxAcceleration value='-1'/>
			<MaxVelocity value='7.33998'/>
			<MaxTorque value='5.428'/>
		</Joint>
		<Child name='Neck'/>
	</RobotNode>


	<RobotNode name='Hip'>
		<Physics>
			<Mass unit='kg' value='1.02338'/>
			<CoM location='Custom' x='0.32' y='0' z='-70.68'/>
			<InertiaMatrix>
					<row1 c1='0.00502422' c2='0' c3='-2.54911e-05'/>
					<row2 c1='0' c2='0.00640971' c3='0.000159449'/>
					<row3 c1='-2.54911e-05' c2='0.000159449' c3='0.00441082'/>
			</InertiaMatrix>
		</Physics>
		<Visualization>
			<File type='inventor'>models/Hip_visu.wrl</File>
		</Visualization>
		<CollisionModel>
			<File type='inventor'>models/Hip_col.wrl</File>
		</CollisionModel>
		<Child name='HipRoll'/>
	</RobotNode>


	<RobotNode name='HipPitch'>
		<Transform>
			<Matrix4x4 units='mm'>
				<row1 c1='1' c2='0' c3='0' c4='0' />
				<row2 c1='0' c2='1' c3='0' c4='0' />
				<row3 c1='0' c2='0' c3='1' c4='268' />
				<row4 c1='0' c2='0' c3='0' c4='1' />
			</Matrix4x4>
		</Transform>
		<Joint type='revolute'>
			<axis x='0' y='-1' z='0'/>
			<limits lo='-1.03847' hi='1.03847' units='radian'/>
			<MaxAcceleration value='-1'/>
			<MaxVelocity value='2.93276'/>
			<MaxTorque value='19.787'/>
		</Joint>
		<Child name='Hip'/>
	</RobotNode>


	<RobotNode name='HipPitch_shiny'>
		<Physics>
			<Mass unit='kg' value='0'/>
			<CoM location='Custom' x='0' y='0' z='268'/>
			<InertiaMatrix>
					<row1 c1='1' c2='0' c3='0'/>
					<row2 c1='0' c2='1' c3='0'/>
					<row3 c1='0' c2='0' c3='1'/>
			</InertiaMatrix>
		</Physics>
	</RobotNode>


	<RobotNode name='HipPitch_shiny_joint'>
		<Joint type='prismatic'>
			<translationdirection x='0' y='0' z='0'/>
			<limits lo='-3.14159' hi='3.14159' units='mm'/>
			<MaxAcceleration value='-1'/>
			<MaxVelocity value='-1'/>
			<MaxTorque value='-1'/>
		</Joint>
		<Child name='HipPitch_shiny'/>
	</RobotNode>


	<RobotNode name='HipRoll'>
		<Transform>
			<Matrix4x4 units='mm'>
				<row1 c1='1' c2='0' c3='0' c4='-0.02' />
				<row2 c1='0' c2='1' c3='0' c4='0' />
				<row3 c1='0' c2='0' c3='1' c4='79' />
				<row4 c1='0' c2='0' c3='0' c4='1' />
			</Matrix4x4>
		</Transform>
		<Joint type='revolute'>
			<axis x='-1' y='0' z='0'/>
			<limits lo='-0.514872' hi='0.514872' units='radian'/>
			<MaxAcceleration value='-1'/>
			<MaxVelocity value='2.27032'/>
			<MaxTorque value='10.1884'/>
		</Joint>
		<Child name='torso'/>
	</RobotNode>


	<RobotNode name='ImuBaseAccelerometer_frame'>
		<Physics>
			<Mass unit='kg' value='0'/>
			<CoM location='Custom' x='0' y='0' z='0'/>
			<InertiaMatrix>
					<row1 c1='1' c2='0' c3='0'/>
					<row2 c1='0' c2='1' c3='0'/>
					<row3 c1='0' c2='0' c3='1'/>
			</InertiaMatrix>
		</Physics>
	</RobotNode>


	<RobotNode name='ImuTorsoAccelerometer_frame'>
		<Physics>
			<Mass unit='kg' value='0'/>
			<CoM location='Custom' x='0' y='0' z='0'/>
			<InertiaMatrix>
					<row1 c1='1' c2='0' c3='0'/>
					<row2 c1='0' c2='1' c3='0'/>
					<row3 c1='0' c2='0' c3='1'/>
			</InertiaMatrix>
		</Physics>
	</RobotNode>


	<RobotNode name='ImuTorsoGyrometer_frame'>
		<Physics>
			<Mass unit='kg' value='0'/>
			<CoM location='Custom' x='0' y='0' z='0'/>
			<InertiaMatrix>
					<row1 c1='1' c2='0' c3='0'/>
					<row2 c1='0' c2='1' c3='0'/>
					<row3 c1='0' c2='0' c3='1'/>
			</InertiaMatrix>
		</Physics>
	</RobotNode>


	<RobotNode name='KneePitch'>
		<Joint type='revolute'>
			<axis x='0' y='-1' z='0'/>
			<limits lo='-0.514872' hi='0.514872' units='radian'/>
			<MaxAcceleration value='-1'/>
			<MaxVelocity value='2.93276'/>
			<MaxTorque value='27.702'/>
		</Joint>
		<Child name='Pelvis'/>
	</RobotNode>


	<RobotNode name='KneePitch_milky'>
		<Physics>
			<Mass unit='kg' value='0'/>
			<CoM location='Custom' x='0' y='0' z='0'/>
			<InertiaMatrix>
					<row1 c1='1' c2='0' c3='0'/>
					<row2 c1='0' c2='1' c3='0'/>
					<row3 c1='0' c2='0' c3='1'/>
			</InertiaMatrix>
		</Physics>
	</RobotNode>


	<RobotNode name='KneePitch_milky_joint'>
		<Joint type='prismatic'>
			<translationdirection x='0' y='0' z='0'/>
			<limits lo='-3.14159' hi='3.14159' units='mm'/>
			<MaxAcceleration value='-1'/>
			<MaxVelocity value='-1'/>
			<MaxTorque value='-1'/>
		</Joint>
		<Child name='KneePitch_milky'/>
	</RobotNode>


	<RobotNode name='LBicep'>
		<Physics>
			<Mass unit='kg' value='0.50527'/>
			<CoM location='Custom' x='81.51' y='12.84' z='-10.17'/>
			<InertiaMatrix>
					<row1 c1='0.000500872' c2='-3.55918e-05' c3='8.51263e-05'/>
					<row2 c1='-3.55918e-05' c2='0.00126284' c3='9.06813e-06'/>
					<row3 c1='8.51263e-05' c2='9.06813e-06' c3='0.00115718'/>
			</InertiaMatrix>
		</Physics>
		<Visualization>
			<File type='inventor'>models/LBicep_visu.wrl</File>
		</Visualization>
		<CollisionModel>
			<File type='inventor'>models/LBicep_col.wrl</File>
		</CollisionModel>
		<Child name='LElbowYaw'/>
		<Child name='LShoulderRoll_shiny_joint'/>
	</RobotNode>


	<RobotNode name='LElbow'>
		<Physics>
			<Mass unit='kg' value='0.27495'/>
			<CoM location='Custom' x='-22.97' y='-0.19' z='1.19'/>
			<InertiaMatrix>
					<row1 c1='0.000122971' c2='9.86024e-07' c3='-2.55838e-05'/>
					<row2 c1='9.86024e-07' c2='0.000331766' c3='-1.98925e-06'/>
					<row3 c1='-2.55838e-05' c2='-1.98925e-06' c3='0.000303047'/>
			</InertiaMatrix>
		</Physics>
		<Visualization>
			<File type='inventor'>models/LElbow_visu.wrl</File>
		</Visualization>
		<CollisionModel>
			<File type='inventor'>models/LElbow_col.wrl</File>
		</CollisionModel>
		<Child name='LElbowRoll'/>
	</RobotNode>


	<RobotNode name='LElbowRoll'>
		<Joint type='revolute'>
			<axis x='0' y='0' z='1'/>
			<limits lo='-1.56207' hi='-0.00872665' units='radian'/>
			<MaxAcceleration value='-1'/>
			<MaxVelocity value='9.22756'/>
			<MaxTorque value='2.666'/>
		</Joint>
		<Child name='LForeArm'/>
	</RobotNode>


	<RobotNode name='LElbowRoll_milky'>
		<Physics>
			<Mass unit='kg' value='0'/>
			<CoM location='Custom' x='0' y='0' z='0'/>
			<InertiaMatrix>
					<row1 c1='1' c2='0' c3='0'/>
					<row2 c1='0' c2='1' c3='0'/>
					<row3 c1='0' c2='0' c3='1'/>
			</InertiaMatrix>
		</Physics>
	</RobotNode>


	<RobotNode name='LElbowRoll_milky_joint'>
		<Joint type='prismatic'>
			<translationdirection x='0' y='0' z='0'/>
			<limits lo='-3.14159' hi='3.14159' units='mm'/>
			<MaxAcceleration value='-1'/>
			<MaxVelocity value='-1'/>
			<MaxTorque value='-1'/>
		</Joint>
		<Child name='LElbowRoll_milky'/>
	</RobotNode>


	<RobotNode name='LElbowYaw'>
		<Transform>
			<Matrix4x4 units='mm'>
				<row1 c1='0.987688' c2='-0' c3='-0.156434' c4='181.2' />
				<row2 c1='0' c2='1' c3='-0' c4='15' />
				<row3 c1='0.156434' c2='0' c3='0.987688' c4='0.13' />
				<row4 c1='0' c2='0' c3='0' c4='1' />
			</Matrix4x4>
		</Transform>
		<Joint type='revolute'>
			<axis x='1' y='0' z='0'/>
			<limits lo='-2.08567' hi='2.08567' units='radian'/>
			<MaxAcceleration value='-1'/>
			<MaxVelocity value='7.33998'/>
			<MaxTorque value='5.428'/>
		</Joint>
		<Child name='LElbow'/>
	</RobotNode>

	<RobotNode name='LForeArm'>
		<Physics>
			<Mass unit='kg' value='0.16579'/>
			<CoM location='Custom' x='59.3' y='2.71' z='-10.14'/>
			<InertiaMatrix>
					<row1 c1='0.00156513' c2='1.47517e-05' c3='-6.05746e-05'/>
					<row2 c1='1.47517e-05' c2='0.00173219' c3='-1.7619e-07'/>
					<row3 c1='-6.05746e-05' c2='-1.7619e-07' c3='0.000273081'/>
			</InertiaMatrix>
		</Physics>
		<Visualization>
			<File type='inventor'>models/LForeArm_visu.wrl</File>
		</Visualization>
		<CollisionModel>
			<File type='inventor'>models/LForeArm_col.wrl</File>
		</CollisionModel>
		<Child name='LElbowRoll_milky_joint'/>
		<Child name='EndArmL'/>
	</RobotNode>


	<RobotNode name='LShoulder'>
		<Physics>
			<Mass unit='kg' value='0.3125'/>
			<CoM location='Custom' x='0.18' y='-18.56' z='0.99'/>
			<InertiaMatrix>
					<row1 c1='0.000361198' c2='-1.98347e-06' c3='6.35907e-07'/>
					<row2 c1='-1.98347e-06' c2='0.000137229' c3='-5.68878e-06'/>
					<row3 c1='6.35907e-07' c2='-5.68878e-06' c3='0.000399194'/>
			</InertiaMatrix>
		</Physics>
		<Visualization>
			<File type='inventor'>models/LShoulder_visu.wrl</File>
		</Visualization>
		<CollisionModel>
			<File type='inventor'>models/LShoulder_col.wrl</File>
		</CollisionModel>
		<Child name='LShoulderRoll'/>
	</RobotNode>


	<RobotNode name='LShoulderPitch'>
		<Transform>
			<Matrix4x4 units='mm'>
				<row1 c1='1' c2='0' c3='0' c4='-57' />
				<row2 c1='0' c2='1' c3='0' c4='149.74' />
				<row3 c1='0' c2='0' c3='1' c4='225.82' />
				<row4 c1='0' c2='0' c3='0' c4='1' />
			</Matrix4x4>
		</Transform>
		<Joint type='revolute'>
			<axis x='0' y='1' z='0'/>
			<limits lo='-2.08567' hi='2.08567' units='radian'/>
			<MaxAcceleration value='-1'/>
			<MaxVelocity value='7.33998'/>
			<MaxTorque value='5.428'/>
		</Joint>
		<Child name='LShoulder'/>
	</RobotNode>


	<RobotNode name='LShoulderRoll'>
		<Joint type='revolute'>
			<axis x='0' y='0' z='1'/>
			<limits lo='0.00872665' hi='1.56207' units='radian'/>
			<MaxAcceleration value='-1'/>
			<MaxVelocity value='9.22756'/>
			<MaxTorque value='2.666'/>
		</Joint>
		<Child name='LBicep'/>
	</RobotNode>


	<RobotNode name='LShoulderRoll_shiny'>
		<Physics>
			<Mass unit='kg' value='0'/>
			<CoM location='Custom' x='0' y='0' z='0'/>
			<InertiaMatrix>
					<row1 c1='1' c2='0' c3='0'/>
					<row2 c1='0' c2='1' c3='0'/>
					<row3 c1='0' c2='0' c3='1'/>
			</InertiaMatrix>
		</Physics>
	</RobotNode>


	<RobotNode name='LShoulderRoll_shiny_joint'>
		<Joint type='prismatic'>
			<translationdirection x='0' y='0' z='0'/>
			<limits lo='-3.14159' hi='3.14159' units='mm'/>
			<MaxAcceleration value='-1'/>
			<MaxVelocity value='-1'/>
			<MaxTorque value='-1'/>
		</Joint>
		<Child name='LShoulderRoll_shiny'/>
	</RobotNode>


	<RobotNode name='LSpeaker_frame'>
		<Physics>
			<Mass unit='kg' value='0'/>
			<CoM location='Custom' x='0' y='0' z='0'/>
			<InertiaMatrix>
					<row1 c1='1' c2='0' c3='0'/>
					<row2 c1='0' c2='1' c3='0'/>
					<row3 c1='0' c2='0' c3='1'/>
			</InertiaMatrix>
		</Physics>
	</RobotNode>

	<RobotNode name='LaserSensor/Front_projected_sensor_fixedjoint'>
		<Transform>
			<Matrix4x4 units='mm'>
				<row1 c1='1' c2='0' c3='0' c4='56.2' />
				<row2 c1='0' c2='1' c3='0' c4='0' />
				<row3 c1='0' c2='0' c3='1' c4='-334' />
				<row4 c1='0' c2='0' c3='0' c4='1' />
			</Matrix4x4>
		</Transform>
		<Joint type='prismatic'>
			<translationdirection x='0' y='0' z='0'/>
			<limits lo='-3.14159' hi='3.14159' units='mm'/>
			<MaxAcceleration value='-1'/>
			<MaxVelocity value='-1'/>
			<MaxTorque value='-1'/>
		</Joint>
		<Child name='SurroundingFrontLaser_frame'/>
	</RobotNode>


	<RobotNode name='LaserSensor/Front_sensor_fixedjoint'>
		<Transform>
			<Matrix4x4 units='mm'>
				<row1 c1='0.939693' c2='0' c3='0.34202' c4='56.2' />
				<row2 c1='0' c2='1' c3='0' c4='0' />
				<row3 c1='-0.34202' c2='0' c3='0.939693' c4='-69.2' />
				<row4 c1='0' c2='0' c3='0' c4='1' />
			</Matrix4x4>
		</Transform>
		<Joint type='prismatic'>
			<translationdirection x='0' y='0' z='0'/>
			<limits lo='-3.14159' hi='3.14159' units='mm'/>
			<MaxAcceleration value='-1'/>
			<MaxVelocity value='-1'/>
			<MaxTorque value='-1'/>
		</Joint>
		<Child name='SurroundingFrontLaser_device_frame'/>
	</RobotNode>


	<RobotNode name='LaserSensor/Left_projected_sensor_fixedjoint'>
		<Transform>
			<Matrix4x4 units='mm'>
				<row1 c1='-0.185405' c2='-0.982662' c3='0' c4='-18' />
				<row2 c1='0.982662' c2='-0.185405' c3='0' c4='89.9' />
				<row3 c1='0' c2='0' c3='1' c4='-334' />
				<row4 c1='0' c2='0' c3='0' c4='1' />
			</Matrix4x4>
		</Transform>
		<Joint type='prismatic'>
			<translationdirection x='0' y='0' z='0'/>
			<limits lo='-3.14159' hi='3.14159' units='mm'/>
			<MaxAcceleration value='-1'/>
			<MaxVelocity value='-1'/>
			<MaxTorque value='-1'/>
		</Joint>
		<Child name='SurroundingLeftLaser_frame'/>
	</RobotNode>


	<RobotNode name='LaserSensor/Left_sensor_fixedjoint'>
		<Transform>
			<Matrix4x4 units='mm'>
				<row1 c1='-3.57628e-06' c2='-1' c3='-1.2517e-06' c4='-18' />
				<row2 c1='0.939693' c2='-3.8147e-06' c3='0.34202' c4='89.9' />
				<row3 c1='-0.34202' c2='1.49012e-08' c3='0.939693' c4='-75.9' />
				<row4 c1='0' c2='0' c3='0' c4='1' />
			</Matrix4x4>
		</Transform>
		<Joint type='prismatic'>
			<translationdirection x='0' y='0' z='0'/>
			<limits lo='-3.14159' hi='3.14159' units='mm'/>
			<MaxAcceleration value='-1'/>
			<MaxVelocity value='-1'/>
			<MaxTorque value='-1'/>
		</Joint>
		<Child name='SurroundingLeftLaser_device_frame'/>
	</RobotNode>


	<RobotNode name='LaserSensor/Right_projected_sensor_fixedjoint'>
		<Transform>
			<Matrix4x4 units='mm'>
				<row1 c1='-0.185405' c2='0.982662' c3='0' c4='-18' />
				<row2 c1='-0.982662' c2='-0.185405' c3='-0' c4='-89.9' />
				<row3 c1='-0' c2='0' c3='1' c4='-334' />
				<row4 c1='0' c2='0' c3='0' c4='1' />
			</Matrix4x4>
		</Transform>
		<Joint type='prismatic'>
			<translationdirection x='0' y='0' z='0'/>
			<limits lo='-3.14159' hi='3.14159' units='mm'/>
			<MaxAcceleration value='-1'/>
			<MaxVelocity value='-1'/>
			<MaxTorque value='-1'/>
		</Joint>
		<Child name='SurroundingRightLaser_frame'/>
	</RobotNode>


	<RobotNode name='LaserSensor/Right_sensor_fixedjoint'>
		<Transform>
			<Matrix4x4 units='mm'>
				<row1 c1='-3.57628e-06' c2='1' c3='-1.2517e-06' c4='-18' />
				<row2 c1='-0.939693' c2='-3.8147e-06' c3='-0.34202' c4='-89.9' />
				<row3 c1='-0.34202' c2='-1.49012e-08' c3='0.939693' c4='-75.9' />
				<row4 c1='0' c2='0' c3='0' c4='1' />
			</Matrix4x4>
		</Transform>
		<Joint type='prismatic'>
			<translationdirection x='0' y='0' z='0'/>
			<limits lo='-3.14159' hi='3.14159' units='mm'/>
			<MaxAcceleration value='-1'/>
			<MaxVelocity value='-1'/>
			<MaxTorque value='-1'/>
		</Joint>
		<Child name='SurroundingRightLaser_device_frame'/>
	</RobotNode>


	<RobotNode name='LaserSensor/Shovel_sensor_fixedjoint'>
		<Transform>
			<Matrix4x4 units='mm'>
				<row1 c1='0.939693' c2='0' c3='0.34202' c4='56.2' />
				<row2 c1='0' c2='1' c3='0' c4='0' />
				<row3 c1='-0.34202' c2='0' c3='0.939693' c4='-69.2' />
				<row4 c1='0' c2='0' c3='0' c4='1' />
			</Matrix4x4>
		</Transform>
		<Joint type='prismatic'>
			<translationdirection x='0' y='0' z='0'/>
			<limits lo='-3.14159' hi='3.14159' units='mm'/>
			<MaxAcceleration value='-1'/>
			<MaxVelocity value='-1'/>
			<MaxTorque value='-1'/>
		</Joint>
		<Child name='ShovelLaser_frame'/>
	</RobotNode>


	<RobotNode name='LaserSensor/VerticalLeft_sensor_fixedjoint'>
		<Transform>
			<Matrix4x4 units='mm'>
				<row1 c1='0.939693' c2='0' c3='0.34202' c4='56.2' />
				<row2 c1='0' c2='1' c3='0' c4='0' />
				<row3 c1='-0.34202' c2='0' c3='0.939693' c4='-69.2' />
				<row4 c1='0' c2='0' c3='0' c4='1' />
			</Matrix4x4>
		</Transform>
		<Joint type='prismatic'>
			<translationdirection x='0' y='0' z='0'/>
			<limits lo='-3.14159' hi='3.14159' units='mm'/>
			<MaxAcceleration value='-1'/>
			<MaxVelocity value='-1'/>
			<MaxTorque value='-1'/>
		</Joint>
		<Child name='VerticalLeftLaser_frame'/>
	</RobotNode>


	<RobotNode name='LaserSensor/VerticalRight_sensor_fixedjoint'>
		<Transform>
			<Matrix4x4 units='mm'>
				<row1 c1='0.939693' c2='0' c3='0.34202' c4='56.2' />
				<row2 c1='0' c2='1' c3='0' c4='0' />
				<row3 c1='-0.34202' c2='0' c3='0.939693' c4='-69.2' />
				<row4 c1='0' c2='0' c3='0' c4='1' />
			</Matrix4x4>
		</Transform>
		<Joint type='prismatic'>
			<translationdirection x='0' y='0' z='0'/>
			<limits lo='-3.14159' hi='3.14159' units='mm'/>
			<MaxAcceleration value='-1'/>
			<MaxVelocity value='-1'/>
			<MaxTorque value='-1'/>
		</Joint>
		<Child name='VerticalRightLaser_frame'/>
	</RobotNode>


	<RobotNode name='Neck'>
		<Physics>
			<Mass unit='kg' value='0.27391'/>
			<CoM location='Custom' x='-2.07' y='0' z='-26.36'/>
			<InertiaMatrix>
					<row1 c1='0.000343501' c2='0' c3='-1.88563e-05'/>
					<row2 c1='0' c2='0.000493898' c3='2.09863e-06'/>
					<row3 c1='-1.88563e-05' c2='2.09863e-06' c3='0.000215252'/>
			</InertiaMatrix>
		</Physics>
		<Visualization>
			<File type='inventor'>models/Neck_visu.wrl</File>
		</Visualization>
		<CollisionModel>
			<File type='inventor'>models/Neck_col.wrl</File>
		</CollisionModel>
		<Child name='HeadPitch'/>
	</RobotNode>


	<RobotNode name='Pelvis'>
		<Physics>
			<Mass unit='kg' value='2.45917'/>
			<CoM location='Custom' x='2.37' y='0' z='-17.54'/>
			<InertiaMatrix>
					<row1 c1='0.034351' c2='0' c3='0.000223034'/>
					<row2 c1='0' c2='0.0303122' c3='-8.37542e-05'/>
					<row3 c1='0.000223034' c2='-8.37542e-05' c3='0.0143771'/>
			</InertiaMatrix>
		</Physics>
		<Visualization>
			<File type='inventor'>models/Pelvis_visu.wrl</File>
		</Visualization>
		<CollisionModel>
			<File type='inventor'>models/Pelvis_col.wrl</File>
		</CollisionModel>
		<Child name='HipPitch'/>
		<Child name='HipPitch_shiny_joint'/>
	</RobotNode>


	<RobotNode name='RBicep'>
		<Physics>
			<Mass unit='kg' value='0.50527'/>
			<CoM location='Custom' x='81.51' y='-12.84' z='-10.17'/>
			<InertiaMatrix>
					<row1 c1='0.000500872' c2='3.55918e-05' c3='8.51263e-05'/>
					<row2 c1='3.55918e-05' c2='0.00126284' c3='-9.06813e-06'/>
					<row3 c1='8.51263e-05' c2='-9.06813e-06' c3='0.00115718'/>
			</InertiaMatrix>
		</Physics>
		<Visualization>
			<File type='inventor'>models/RBicep_visu.wrl</File>
		</Visualization>
		<CollisionModel>
			<File type='inventor'>models/RBicep_col.wrl</File>
		</CollisionModel>
		<Child name='RElbowYaw'/>
		<Child name='RShoulderRoll_shiny_joint'/>
	</RobotNode>


	<RobotNode name='RElbow'>
		<Physics>
			<Mass unit='kg' value='0.27495'/>
			<CoM location='Custom' x='-22.97' y='0.19' z='1.19'/>
			<InertiaMatrix>
					<row1 c1='0.000122971' c2='-9.86024e-07' c3='-2.55838e-05'/>
					<row2 c1='-9.86024e-07' c2='0.000331766' c3='1.98925e-06'/>
					<row3 c1='-2.55838e-05' c2='1.98925e-06' c3='0.000303047'/>
			</InertiaMatrix>
		</Physics>
		<Visualization>
			<File type='inventor'>models/RElbow_visu.wrl</File>
		</Visualization>
		<CollisionModel>
			<File type='inventor'>models/RElbow_col.wrl</File>
		</CollisionModel>
		<Child name='RElbowRoll'/>
	</RobotNode>


	<RobotNode name='RElbowRoll'>
		<Joint type='revolute'>
			<axis x='0' y='0' z='1'/>
			<limits lo='0.00872665' hi='1.56207' units='radian'/>
			<MaxAcceleration value='-1'/>
			<MaxVelocity value='9.22756'/>
			<MaxTorque value='2.666'/>
		</Joint>
		<Child name='RForeArm'/>
	</RobotNode>


	<RobotNode name='RElbowRoll_milky'>
		<Physics>
			<Mass unit='kg' value='0'/>
			<CoM location='Custom' x='0' y='0' z='0'/>
			<InertiaMatrix>
					<row1 c1='1' c2='0' c3='0'/>
					<row2 c1='0' c2='1' c3='0'/>
					<row3 c1='0' c2='0' c3='1'/>
			</InertiaMatrix>
		</Physics>
	</RobotNode>


	<RobotNode name='RElbowRoll_milky_joint'>
		<Joint type='prismatic'>
			<translationdirection x='0' y='0' z='0'/>
			<limits lo='-3.14159' hi='3.14159' units='mm'/>
			<MaxAcceleration value='-1'/>
			<MaxVelocity value='-1'/>
			<MaxTorque value='-1'/>
		</Joint>
		<Child name='RElbowRoll_milky'/>
	</RobotNode>


	<RobotNode name='RElbowYaw'>
		<Transform>
			<Matrix4x4 units='mm'>
				<row1 c1='0.987688' c2='-0' c3='-0.156434' c4='181.2' />
				<row2 c1='0' c2='1' c3='-0' c4='-15' />
				<row3 c1='0.156434' c2='0' c3='0.987688' c4='0.13' />
				<row4 c1='0' c2='0' c3='0' c4='1' />
			</Matrix4x4>
		</Transform>
		<Joint type='revolute'>
			<axis x='1' y='0' z='0'/>
			<limits lo='-2.08567' hi='2.08567' units='radian'/>
			<MaxAcceleration value='-1'/>
			<MaxVelocity value='7.33998'/>
			<MaxTorque value='5.428'/>
		</Joint>
		<Child name='RElbow'/>
	</RobotNode>




	<RobotNode name='RForeArm'>
		<Physics>
			<Mass unit='kg' value='0.16579'/>
			<CoM location='Custom' x='59.3' y='-2.71' z='-10.14'/>
			<InertiaMatrix>
					<row1 c1='0.00156513' c2='-1.47517e-05' c3='-6.05746e-05'/>
					<row2 c1='-1.47517e-05' c2='0.00173219' c3='1.7619e-07'/>
					<row3 c1='-6.05746e-05' c2='1.7619e-07' c3='0.000273081'/>
			</InertiaMatrix>
		</Physics>
		<Visualization>
			<File type='inventor'>models/RForeArm_visu.wrl</File>
		</Visualization>
		<CollisionModel>
			<File type='inventor'>models/RForeArm_col.wrl</File>
		</CollisionModel>
		<Child name='RElbowRoll_milky_joint'/>
		<!-- link to the EndEffector -->
		<Child name='RWristYaw'/>
	</RobotNode>
		<RobotNode name='RWristYaw'>
		<Transform>
			<Matrix4x4 units='mm'>
				<row1 c1='1' c2='0' c3='0' c4='150' />
				<row2 c1='0' c2='1' c3='0' c4='0' />
				<row3 c1='0' c2='0' c3='1' c4='0' />
				<row4 c1='0' c2='0' c3='0' c4='1' />
			</Matrix4x4>
		</Transform>
		<Joint type='revolute'>
			<axis x='-1' y='0' z='0'/>
			<limits lo='-1.82387' hi='1.82387' units='radian'/>
			<MaxAcceleration value='-1'/>
			<MaxVelocity value='17.3835'/>
			<MaxTorque value='0.2014'/>
		</Joint>
		<Child name='EndArmR'/>
	</RobotNode>

	<RobotNode name='RShoulder'>
		<Physics>
			<Mass unit='kg' value='0.3125'/>
			<CoM location='Custom' x='0.18' y='18.56' z='0.99'/>
			<InertiaMatrix>
					<row1 c1='0.000361198' c2='1.98347e-06' c3='6.35907e-07'/>
					<row2 c1='1.98347e-06' c2='0.000137229' c3='5.68878e-06'/>
					<row3 c1='6.35907e-07' c2='5.68878e-06' c3='0.000399194'/>
			</InertiaMatrix>
		</Physics>
		<Visualization>
			<File type='inventor'>models/RShoulder_visu.wrl</File>
		</Visualization>
		<CollisionModel>
			<File type='inventor'>models/RShoulder_col.wrl</File>
		</CollisionModel>
		<Child name='RShoulderRoll'/>
	</RobotNode>


	<RobotNode name='RShoulderPitch'>
		<Transform>
			<Matrix4x4 units='mm'>
				<row1 c1='1' c2='0' c3='0' c4='-57' />
				<row2 c1='0' c2='1' c3='0' c4='-149.74' />
				<row3 c1='0' c2='0' c3='1' c4='225.82' />
				<row4 c1='0' c2='0' c3='0' c4='1' />
			</Matrix4x4>
		</Transform>
		<Joint type='revolute'>
			<axis x='0' y='1' z='0'/>
			<limits lo='-2.08567' hi='2.08567' units='radian'/>
			<MaxAcceleration value='-1'/>
			<MaxVelocity value='7.33998'/>
			<MaxTorque value='5.428'/>
		</Joint>
		<Child name='RShoulder'/>
	</RobotNode>


	<RobotNode name='RShoulderRoll'>
		<Joint type='revolute'>
			<axis x='0' y='0' z='1'/>
			<limits lo='-1.56207' hi='-0.00872665' units='radian'/>
			<MaxAcceleration value='-1'/>
			<MaxVelocity value='9.22756'/>
			<MaxTorque value='2.666'/>
		</Joint>
		<Child name='RBicep'/>
	</RobotNode>


	<RobotNode name='RShoulderRoll_shiny'>
		<Physics>
			<Mass unit='kg' value='0'/>
			<CoM location='Custom' x='0' y='0' z='0'/>
			<InertiaMatrix>
					<row1 c1='1' c2='0' c3='0'/>
					<row2 c1='0' c2='1' c3='0'/>
					<row3 c1='0' c2='0' c3='1'/>
			</InertiaMatrix>
		</Physics>
	</RobotNode>


	<RobotNode name='RShoulderRoll_shiny_joint'>
		<Joint type='prismatic'>
			<translationdirection x='0' y='0' z='0'/>
			<limits lo='-3.14159' hi='3.14159' units='mm'/>
			<MaxAcceleration value='-1'/>
			<MaxVelocity value='-1'/>
			<MaxTorque value='-1'/>
		</Joint>
		<Child name='RShoulderRoll_shiny'/>
	</RobotNode>


	<RobotNode name='RSpeaker_frame'>
		<Physics>
			<Mass unit='kg' value='0'/>
			<CoM location='Custom' x='0' y='0' z='0'/>
			<InertiaMatrix>
					<row1 c1='1' c2='0' c3='0'/>
					<row2 c1='0' c2='1' c3='0'/>
					<row3 c1='0' c2='0' c3='1'/>
			</InertiaMatrix>
		</Physics>
	</RobotNode>

	<RobotNode name='ShovelLaser_frame'>
		<Physics>
			<Mass unit='kg' value='0'/>
			<CoM location='Custom' x='0' y='0' z='0'/>
			<InertiaMatrix>
					<row1 c1='1' c2='0' c3='0'/>
					<row2 c1='0' c2='1' c3='0'/>
					<row3 c1='0' c2='0' c3='1'/>
			</InertiaMatrix>
		</Physics>
	</RobotNode>


	<RobotNode name='Sonar/Back_sensor_fixedjoint'>
		<Transform>
			<Matrix4x4 units='mm'>
				<row1 c1='-0.978148' c2='2.64981e-06' c3='0.20791' c4='-71.8' />
				<row2 c1='-2.5956e-06' c2='-1' c3='5.33532e-07' c4='0' />
				<row3 c1='0.20791' c2='-1.77789e-08' c3='0.978148' c4='-53.4' />
				<row4 c1='0' c2='0' c3='0' c4='1' />
			</Matrix4x4>
		</Transform>
		<Joint type='prismatic'>
			<translationdirection x='0' y='0' z='0'/>
			<limits lo='-3.14159' hi='3.14159' units='mm'/>
			<MaxAcceleration value='-1'/>
			<MaxVelocity value='-1'/>
			<MaxTorque value='-1'/>
		</Joint>
		<Child name='SonarBack_frame'/>
	</RobotNode>


	<RobotNode name='Sonar/Front_sensor_fixedjoint'>
		<Transform>
			<Matrix4x4 units='mm'>
				<row1 c1='0.948332' c2='-0' c3='-0.317278' c4='69.9' />
				<row2 c1='0' c2='1' c3='-0' c4='0' />
				<row3 c1='0.317278' c2='0' c3='0.948332' c4='-102.3' />
				<row4 c1='0' c2='0' c3='0' c4='1' />
			</Matrix4x4>
		</Transform>
		<Joint type='prismatic'>
			<translationdirection x='0' y='0' z='0'/>
			<limits lo='-3.14159' hi='3.14159' units='mm'/>
			<MaxAcceleration value='-1'/>
			<MaxVelocity value='-1'/>
			<MaxTorque value='-1'/>
		</Joint>
		<Child name='SonarFront_frame'/>
	</RobotNode>


	<RobotNode name='SonarBack_frame'>
		<Physics>
			<Mass unit='kg' value='0'/>
			<CoM location='Custom' x='0' y='0' z='0'/>
			<InertiaMatrix>
					<row1 c1='1' c2='0' c3='0'/>
					<row2 c1='0' c2='1' c3='0'/>
					<row3 c1='0' c2='0' c3='1'/>
			</InertiaMatrix>
		</Physics>
	</RobotNode>


	<RobotNode name='SonarFront_frame'>
		<Physics>
			<Mass unit='kg' value='0'/>
			<CoM location='Custom' x='0' y='0' z='0'/>
			<InertiaMatrix>
					<row1 c1='1' c2='0' c3='0'/>
					<row2 c1='0' c2='1' c3='0'/>
					<row3 c1='0' c2='0' c3='1'/>
			</InertiaMatrix>
		</Physics>
	</RobotNode>


	<RobotNode name='SpeakerLeft_sensor_fixedjoint'>
		<Joint type='prismatic'>
			<translationdirection x='0' y='0' z='0'/>
			<limits lo='-3.14159' hi='3.14159' units='mm'/>
			<MaxAcceleration value='-1'/>
			<MaxVelocity value='-1'/>
			<MaxTorque value='-1'/>
		</Joint>
		<Child name='LSpeaker_frame'/>
	</RobotNode>


	<RobotNode name='SpeakerRight_sensor_fixedjoint'>
		<Joint type='prismatic'>
			<translationdirection x='0' y='0' z='0'/>
			<limits lo='-3.14159' hi='3.14159' units='mm'/>
			<MaxAcceleration value='-1'/>
			<MaxVelocity value='-1'/>
			<MaxTorque value='-1'/>
		</Joint>
		<Child name='RSpeaker_frame'/>
	</RobotNode>


	<RobotNode name='SurroundingFrontLaser_device_frame'>
		<Physics>
			<Mass unit='kg' value='0'/>
			<CoM location='Custom' x='0' y='0' z='0'/>
			<InertiaMatrix>
					<row1 c1='1' c2='0' c3='0'/>
					<row2 c1='0' c2='1' c3='0'/>
					<row3 c1='0' c2='0' c3='1'/>
			</InertiaMatrix>
		</Physics>
	</RobotNode>


	<RobotNode name='SurroundingFrontLaser_frame'>
		<Physics>
			<Mass unit='kg' value='0'/>
			<CoM location='Custom' x='0' y='0' z='0'/>
			<InertiaMatrix>
					<row1 c1='1' c2='0' c3='0'/>
					<row2 c1='0' c2='1' c3='0'/>
					<row3 c1='0' c2='0' c3='1'/>
			</InertiaMatrix>
		</Physics>
	</RobotNode>


	<RobotNode name='SurroundingLeftLaser_device_frame'>
		<Physics>
			<Mass unit='kg' value='0'/>
			<CoM location='Custom' x='0' y='0' z='0'/>
			<InertiaMatrix>
					<row1 c1='1' c2='0' c3='0'/>
					<row2 c1='0' c2='1' c3='0'/>
					<row3 c1='0' c2='0' c3='1'/>
			</InertiaMatrix>
		</Physics>
	</RobotNode>


	<RobotNode name='SurroundingLeftLaser_frame'>
		<Physics>
			<Mass unit='kg' value='0'/>
			<CoM location='Custom' x='0' y='0' z='0'/>
			<InertiaMatrix>
					<row1 c1='1' c2='0' c3='0'/>
					<row2 c1='0' c2='1' c3='0'/>
					<row3 c1='0' c2='0' c3='1'/>
			</InertiaMatrix>
		</Physics>
	</RobotNode>


	<RobotNode name='SurroundingRightLaser_device_frame'>
		<Physics>
			<Mass unit='kg' value='0'/>
			<CoM location='Custom' x='0' y='0' z='0'/>
			<InertiaMatrix>
					<row1 c1='1' c2='0' c3='0'/>
					<row2 c1='0' c2='1' c3='0'/>
					<row3 c1='0' c2='0' c3='1'/>
			</InertiaMatrix>
		</Physics>
	</RobotNode>


	<RobotNode name='SurroundingRightLaser_frame'>
		<Physics>
			<Mass unit='kg' value='0'/>
			<CoM location='Custom' x='0' y='0' z='0'/>
			<InertiaMatrix>
					<row1 c1='1' c2='0' c3='0'/>
					<row2 c1='0' c2='1' c3='0'/>
					<row3 c1='0' c2='0' c3='1'/>
			</InertiaMatrix>
		</Physics>
	</RobotNode>


	<RobotNode name='Tablet_frame'>
		<Physics>
			<Mass unit='kg' value='0'/>
			<CoM location='Custom' x='0' y='0' z='0'/>
			<InertiaMatrix>
					<row1 c1='1' c2='0' c3='0'/>
					<row2 c1='0' c2='1' c3='0'/>
					<row3 c1='0' c2='0' c3='1'/>
			</InertiaMatrix>
		</Physics>
	</RobotNode>


	<RobotNode name='Tablet_sensor_fixedjoint'>
		<Transform>
			<Matrix4x4 units='mm'>
				<row1 c1='0.866025' c2='-0' c3='-0.5' c4='83.9249' />
				<row2 c1='0' c2='1' c3='-0' c4='0' />
				<row3 c1='0.5' c2='0' c3='0.866025' c4='201.51' />
				<row4 c1='0' c2='0' c3='0' c4='1' />
			</Matrix4x4>
		</Transform>
		<Joint type='prismatic'>
			<translationdirection x='0' y='0' z='0'/>
			<limits lo='-3.14159' hi='3.14159' units='mm'/>
			<MaxAcceleration value='-1'/>
			<MaxVelocity value='-1'/>
			<MaxTorque value='-1'/>
		</Joint>
		<Child name='Tablet_frame'/>
	</RobotNode>


	<RobotNode name='Tibia'>
		<Physics>
			<Mass unit='kg' value='11.6015'/>
			<CoM location='Custom' x='2.20451' y='0' z='82.271'/>
			<InertiaMatrix>
					<row1 c1='0.129229' c2='-0.000401943' c3='0.00048556'/>
					<row2 c1='-0.000401943' c2='0.122839' c3='-1.01666e-08'/>
					<row3 c1='0.00048556' c2='-1.01666e-08' c3='0.108168'/>
			</InertiaMatrix>
		</Physics>
		<Visualization>
			<File type='inventor'>models/Tibia_visu.wrl</File>
		</Visualization>
		<CollisionModel>
			<File type='inventor'>models/Tibia_col.wrl</File>
		</CollisionModel>
		<Child name='AccelerometerBase_sensor_fixedjoint'/>
		<Child name='Bumper/Back_sensor_fixedjoint'/>
		<Child name='Bumper/FrontLeft_sensor_fixedjoint'/>
		<Child name='Bumper/FrontRight_sensor_fixedjoint'/>
		<Child name='KneePitch'/>
		<Child name='KneePitch_milky_joint'/>
		<Child name='LaserSensor/Front_projected_sensor_fixedjoint'/>
		<Child name='LaserSensor/Front_sensor_fixedjoint'/>
		<Child name='LaserSensor/Left_projected_sensor_fixedjoint'/>
		<Child name='LaserSensor/Left_sensor_fixedjoint'/>
		<Child name='LaserSensor/Right_projected_sensor_fixedjoint'/>
		<Child name='LaserSensor/Right_sensor_fixedjoint'/>
		<Child name='LaserSensor/Shovel_sensor_fixedjoint'/>
		<Child name='LaserSensor/VerticalLeft_sensor_fixedjoint'/>
		<Child name='LaserSensor/VerticalRight_sensor_fixedjoint'/>
		<Child name='Sonar/Back_sensor_fixedjoint'/>
		<Child name='Sonar/Front_sensor_fixedjoint'/>
		<Child name='WheelB'/>
		<Child name='WheelFL'/>
		<Child name='WheelFR'/>
	</RobotNode>


	<RobotNode name='Torso_shiny'>
		<Physics>
			<Mass unit='kg' value='0'/>
			<CoM location='Custom' x='0' y='0' z='69.5'/>
			<InertiaMatrix>
					<row1 c1='1' c2='0' c3='0'/>
					<row2 c1='0' c2='1' c3='0'/>
					<row3 c1='0' c2='0' c3='1'/>
			</InertiaMatrix>
		</Physics>
	</RobotNode>


	<RobotNode name='Torso_shiny_joint'>
		<Transform>
			<Matrix4x4 units='mm'>
				<row1 c1='1' c2='0' c3='0' c4='0' />
				<row2 c1='0' c2='1' c3='0' c4='0' />
				<row3 c1='0' c2='0' c3='1' c4='69.5' />
				<row4 c1='0' c2='0' c3='0' c4='1' />
			</Matrix4x4>
		</Transform>
		<Joint type='prismatic'>
			<translationdirection x='0' y='0' z='0'/>
			<limits lo='-3.14159' hi='3.14159' units='mm'/>
			<MaxAcceleration value='-1'/>
			<MaxVelocity value='-1'/>
			<MaxTorque value='-1'/>
		</Joint>
		<Child name='Torso_shiny'/>
	</RobotNode>


	<RobotNode name='Torso_transparent'>
		<Physics>
			<Mass unit='kg' value='0'/>
			<CoM location='Custom' x='0' y='0' z='69.5'/>
			<InertiaMatrix>
					<row1 c1='1' c2='0' c3='0'/>
					<row2 c1='0' c2='1' c3='0'/>
					<row3 c1='0' c2='0' c3='1'/>
			</InertiaMatrix>
		</Physics>
	</RobotNode>


	<RobotNode name='Torso_transparent_joint'>
		<Transform>
			<Matrix4x4 units='mm'>
				<row1 c1='1' c2='0' c3='0' c4='0' />
				<row2 c1='0' c2='1' c3='0' c4='0' />
				<row3 c1='0' c2='0' c3='1' c4='69.5' />
				<row4 c1='0' c2='0' c3='0' c4='1' />
			</Matrix4x4>
		</Transform>
		<Joint type='prismatic'>
			<translationdirection x='0' y='0' z='0'/>
			<limits lo='-3.14159' hi='3.14159' units='mm'/>
			<MaxAcceleration value='-1'/>
			<MaxVelocity value='-1'/>
			<MaxTorque value='-1'/>
		</Joint>
		<Child name='Torso_transparent'/>
	</RobotNode>


	<RobotNode name='VerticalLeftLaser_frame'>
		<Physics>
			<Mass unit='kg' value='0'/>
			<CoM location='Custom' x='0' y='0' z='0'/>
			<InertiaMatrix>
					<row1 c1='1' c2='0' c3='0'/>
					<row2 c1='0' c2='1' c3='0'/>
					<row3 c1='0' c2='0' c3='1'/>
			</InertiaMatrix>
		</Physics>
	</RobotNode>


	<RobotNode name='VerticalRightLaser_frame'>
		<Physics>
			<Mass unit='kg' value='0'/>
			<CoM location='Custom' x='0' y='0' z='0'/>
			<InertiaMatrix>
					<row1 c1='1' c2='0' c3='0'/>
					<row2 c1='0' c2='1' c3='0'/>
					<row3 c1='0' c2='0' c3='1'/>
			</InertiaMatrix>
		</Physics>
	</RobotNode>


	<RobotNode name='WheelB'>
		<Transform>
			<Matrix4x4 units='mm'>
				<row1 c1='-1' c2='2.65359e-06' c3='0' c4='-170' />
				<row2 c1='-2.65359e-06' c2='-1' c3='-0' c4='0' />
				<row3 c1='-0' c2='0' c3='1' c4='-264' />
				<row4 c1='0' c2='0' c3='0' c4='1' />
			</Matrix4x4>
		</Transform>
		<Joint type='revolute'>
			<axis x='1' y='0' z='0'/>
			<limits lo='0' hi='0' units='radian'/>
			<MaxAcceleration value='-1'/>
			<MaxVelocity value='6.28319'/>
			<MaxTorque value='3.25'/>
		</Joint>
		<Child name='WheelB_link'/>
	</RobotNode>


	<RobotNode name='WheelB_link'>
		<Physics>
			<Mass unit='kg' value='1.58028'/>
			<CoM location='Custom' x='0' y='0' z='0'/>
			<InertiaMatrix>
					<row1 c1='0.00299756' c2='6.3068e-07' c3='5.56903e-06'/>
					<row2 c1='6.3068e-07' c2='0.00303229' c3='-9.0408e-07'/>
					<row3 c1='5.56903e-06' c2='-9.0408e-07' c3='0.00296585'/>
			</InertiaMatrix>
		</Physics>
		<Visualization>
			<File type='inventor'>models/WheelB_link_visu.wrl</File>
		</Visualization>
		<CollisionModel>
			<File type='inventor'>models/WheelB_link_col.wrl</File>
		</CollisionModel>
	</RobotNode>


	<RobotNode name='WheelFL'>
		<Transform>
			<Matrix4x4 units='mm'>
				<row1 c1='0.475583' c2='-0.879671' c3='0' c4='90' />
				<row2 c1='0.879671' c2='0.475583' c3='0' c4='155' />
				<row3 c1='0' c2='0' c3='1' c4='-264' />
				<row4 c1='0' c2='0' c3='0' c4='1' />
			</Matrix4x4>
		</Transform>
		<Joint type='revolute'>
			<axis x='1' y='0' z='0'/>
			<limits lo='0' hi='0' units='radian'/>
			<MaxAcceleration value='-1'/>
			<MaxVelocity value='6.28319'/>
			<MaxTorque value='3.25'/>
		</Joint>
		<Child name='WheelFL_link'/>
	</RobotNode>


	<RobotNode name='WheelFL_link'>
		<Physics>
			<Mass unit='kg' value='1.58028'/>
			<CoM location='Custom' x='0' y='0' z='0'/>
			<InertiaMatrix>
					<row1 c1='0.00299756' c2='6.3068e-07' c3='5.56903e-06'/>
					<row2 c1='6.3068e-07' c2='0.00303229' c3='-9.0408e-07'/>
					<row3 c1='5.56903e-06' c2='-9.0408e-07' c3='0.00296585'/>
			</InertiaMatrix>
		</Physics>
		<Visualization>
			<File type='inventor'>models/WheelFL_link_visu.wrl</File>
		</Visualization>
		<CollisionModel>
			<File type='inventor'>models/WheelFL_link_col.wrl</File>
		</CollisionModel>
	</RobotNode>


	<RobotNode name='WheelFR'>
		<Transform>
			<Matrix4x4 units='mm'>
				<row1 c1='0.475583' c2='0.879671' c3='0' c4='90' />
				<row2 c1='-0.879671' c2='0.475583' c3='-0' c4='-155' />
				<row3 c1='-0' c2='0' c3='1' c4='-264' />
				<row4 c1='0' c2='0' c3='0' c4='1' />
			</Matrix4x4>
		</Transform>
		<Joint type='revolute'>
			<axis x='1' y='0' z='0'/>
			<limits lo='0' hi='0' units='radian'/>
			<MaxAcceleration value='-1'/>
			<MaxVelocity value='6.28319'/>
			<MaxTorque value='3.25'/>
		</Joint>
		<Child name='WheelFR_link'/>
	</RobotNode>


	<RobotNode name='WheelFR_link'>
		<Physics>
			<Mass unit='kg' value='1.58028'/>
			<CoM location='Custom' x='0' y='0' z='0'/>
			<InertiaMatrix>
					<row1 c1='0.00299756' c2='6.3068e-07' c3='5.56903e-06'/>
					<row2 c1='6.3068e-07' c2='0.00303229' c3='-9.0408e-07'/>
					<row3 c1='5.56903e-06' c2='-9.0408e-07' c3='0.00296585'/>
			</InertiaMatrix>
		</Physics>
		<Visualization>
			<File type='inventor'>models/WheelFR_link_visu.wrl</File>
		</Visualization>
		<CollisionModel>
			<File type='inventor'>models/WheelFR_link_col.wrl</File>
		</CollisionModel>
	</RobotNode>


	<RobotNode name='base_footprint'>
		<Physics>
			<Mass unit='kg' value='0'/>
			<CoM location='Custom' x='0' y='0' z='0'/>
			<InertiaMatrix>
					<row1 c1='1' c2='0' c3='0'/>
					<row2 c1='0' c2='1' c3='0'/>
					<row3 c1='0' c2='0' c3='1'/>
			</InertiaMatrix>
		</Physics>
		<Child name='base_footprint_joint'/>
	</RobotNode>


	<RobotNode name='base_footprint_joint'>
		<Transform>
			<Matrix4x4 units='mm'>
				<row1 c1='1' c2='0' c3='0' c4='0' />
				<row2 c1='0' c2='1' c3='0' c4='0' />
				<row3 c1='0' c2='0' c3='1' c4='334' />
				<row4 c1='0' c2='0' c3='0' c4='1' />
			</Matrix4x4>
		</Transform>
		<Joint type='prismatic'>
			<translationdirection x='0' y='0' z='0'/>
			<limits lo='-3.14159' hi='3.14159' units='mm'/>
			<MaxAcceleration value='-1'/>
			<MaxVelocity value='-1'/>
			<MaxTorque value='-1'/>
		</Joint>
		<Child name='Tibia'/>
	</RobotNode>


	<RobotNode name='base_link'>
		<Physics>
			<Mass unit='kg' value='0'/>
			<CoM location='Custom' x='0' y='0' z='0'/>
			<InertiaMatrix>
					<row1 c1='1' c2='0' c3='0'/>
					<row2 c1='0' c2='1' c3='0'/>
					<row3 c1='0' c2='0' c3='1'/>
			</InertiaMatrix>
		</Physics>
		<Child name='base_link_joint'/>
	</RobotNode>


	<RobotNode name='base_link_joint'>
		<Joint type='prismatic'>
			<translationdirection x='0' y='0' z='0'/>
			<limits lo='-3.14159' hi='3.14159' units='mm'/>
			<MaxAcceleration value='-1'/>
			<MaxVelocity value='-1'/>
			<MaxTorque value='-1'/>
		</Joint>
		<Child name='base_footprint'/>
	</RobotNode>

	<RobotNode name='torso'>
		<Physics>
			<Mass unit='kg' value='3.99533'/>
			<CoM location='Custom' x='3.22' y='0' z='128.71'/>
			<InertiaMatrix>
					<row1 c1='0.0452761' c2='0' c3='0.00499091'/>
					<row2 c1='0' c2='0.0432702' c3='-0.000266886'/>
					<row3 c1='0.00499091' c2='-0.000266886' c3='0.0258881'/>
			</InertiaMatrix>
		</Physics>
		<Visualization>
			<File type='inventor'>models/torso_visu.wrl</File>
		</Visualization>
		<CollisionModel>
			<File type='inventor'>models/torso_col.wrl</File>
		</CollisionModel>
		<Child name='Accelerometer_sensor_fixedjoint'/>
		<Child name='ChestBoard/Button_sensor_fixedjoint'/>
		<Child name='Gyrometer_sensor_fixedjoint'/>
		<Child name='HeadYaw'/>
		<Child name='LShoulderPitch'/>
		<Child name='RShoulderPitch'/>
		<Child name='Tablet_sensor_fixedjoint'/>
		<Child name='Torso_shiny_joint'/>
		<Child name='Torso_transparent_joint'/>
	</RobotNode>

	<!-- Modifications start here -->

	<RobotNode name="EndArmR">
			<Transform>
				<DH a="0" d="0" theta="0" alpha="0" unitsangle="degree" unitslength="mm"/>
			</Transform>
		    <ChildFromRobot>
				<File importEEF="true">pepper_rGripper.xml</File>
			</ChildFromRobot>
	</RobotNode>
	<RobotNode name="EndArmL">
			<Transform>
				<DH a="0" d="0" theta="0" alpha="0" unitsangle="degree" unitslength="mm"/>
			</Transform>
		    <ChildFromRobot>
				<File importEEF="true">LGripper.xml</File>
			</ChildFromRobot>
	</RobotNode>


</Robot>
